{
    "imageHeight": 800,
    "imageWidth": 575,
    "shapes": [
        {
            "label": "Poligon 18",
            "points": [
                [
                    245,
                    9
                ],
                [
                    274,
                    78
                ],
                [
                    271,
                    121
                ],
                [
                    278,
                    169
                ],
                [
                    300,
                    212
                ],
                [
                    310,
                    266
                ],
                [
                    320,
                    325
                ],
                [
                    327,
                    362
                ],
                [
                    327,
                    403
                ],
                [
                    330,
                    474
                ],
                [
                    327,
                    537
                ],
                [
                    315,
                    595
                ],
                [
                    299,
                    644
                ],
                [
                    279,
                    684
                ],
                [
                    246,
                    720
                ],
                [
                    239,
                    757
                ],
                [
                    205,
                    779
                ],
                [
                    250,
                    782
                ],
                [
                    282,
                    768
                ],
                [
                    333,
                    717
                ],
                [
                    362,
                    692
                ],
                [
                    390,
                    652
                ],
                [
                    408,
                    592
                ],
                [
                    417,
                    552
                ],
                [
                    415,
                    492
                ],
                [
                    404,
                    443
                ],
                [
                    401,
                    387
                ],
                [
                    396,
                    335
                ],
                [
                    385,
                    295
                ],
                [
                    386,
                    252
                ],
                [
                    380,
                    231
                ],
                [
                    375,
                    190
                ],
                [
                    366,
                    140
                ],
                [
                    357,
                    109
                ],
                [
                    353,
                    62
                ],
                [
                    345,
                    24
                ],
                [
                    339,
                    2
                ],
                [
                    339,
                    5
                ]
            ]
        }
    ]
}