{
    "imageHeight": 448,
    "imageWidth": 448,
    "shapes": [
        {
            "label": "Poligon 46",
            "points": [
                [
                    195,
                    4
                ],
                [
                    204,
                    42
                ],
                [
                    209,
                    78
                ],
                [
                    214,
                    105
                ],
                [
                    219,
                    132
                ],
                [
                    223,
                    155
                ],
                [
                    228,
                    177
                ],
                [
                    241,
                    208
                ],
                [
                    242,
                    239
                ],
                [
                    242,
                    270
                ],
                [
                    241,
                    295
                ],
                [
                    231,
                    328
                ],
                [
                    219,
                    345
                ],
                [
                    201,
                    369
                ],
                [
                    180,
                    387
                ],
                [
                    165,
                    421
                ],
                [
                    154,
                    444
                ],
                [
                    173,
                    441
                ],
                [
                    183,
                    425
                ],
                [
                    193,
                    407
                ],
                [
                    220,
                    391
                ],
                [
                    254,
                    377
                ],
                [
                    272,
                    369
                ],
                [
                    291,
                    358
                ],
                [
                    294,
                    345
                ],
                [
                    297,
                    323
                ],
                [
                    301,
                    299
                ],
                [
                    302,
                    270
                ],
                [
                    299,
                    245
                ],
                [
                    296,
                    220
                ],
                [
                    291,
                    201
                ],
                [
                    287,
                    180
                ],
                [
                    284,
                    157
                ],
                [
                    279,
                    131
                ],
                [
                    276,
                    116
                ],
                [
                    267,
                    99
                ],
                [
                    263,
                    85
                ],
                [
                    256,
                    70
                ],
                [
                    256,
                    51
                ],
                [
                    252,
                    34
                ],
                [
                    251,
                    17
                ],
                [
                    245,
                    5
                ],
                [
                    243,
                    0
                ]
            ]
        }
    ]
}